ats/__init__.py
pyats/awesome.cpython-310-x86_64-linux-gnu.so
pyats/configuration.cpython-310-x86_64-linux-gnu.so
pyats/info.cpython-310-x86_64-linux-gnu.so
pyats/package_data.cpython-310-x86_64-linux-gnu.so
pyats/cli/__init__.py
pyats/cli/__main__.cpython-310-x86_64-linux-gnu.so
pyats/cli/base.cpython-310-x86_64-linux-gnu.so
pyats/cli/core.cpython-310-x86_64-linux-gnu.so
pyats/cli/formatter.cpython-310-x86_64-linux-gnu.so
pyats/cli/parser.cpython-310-x86_64-linux-gnu.so
pyats/cli/utils.cpython-310-x86_64-linux-gnu.so
pyats/cli/commands/__init__.py
pyats/cli/commands/create.cpython-310-x86_64-linux-gnu.so
pyats/cli/commands/run.cpython-310-x86_64-linux-gnu.so
pyats/cli/commands/secret.cpython-310-x86_64-linux-gnu.so
pyats/cli/commands/shell.cpython-310-x86_64-linux-gnu.so
pyats/cli/commands/validate.cpython-310-x86_64-linux-gnu.so
pyats/cli/commands/migrate/__init__.py
pyats/cli/commands/migrate/abstract.cpython-310-x86_64-linux-gnu.so
pyats/cli/commands/version/__init__.py
pyats/cli/commands/version/check.cpython-310-x86_64-linux-gnu.so
pyats/cli/commands/version/check_available.cpython-310-x86_64-linux-gnu.so
pyats/cli/commands/version/template.cpython-310-x86_64-linux-gnu.so
pyats/cli/commands/version/update.cpython-310-x86_64-linux-gnu.so
pyats/manifest/__init__.py
pyats/manifest/commands.cpython-310-x86_64-linux-gnu.so
pyats/manifest/manifest.cpython-310-x86_64-linux-gnu.so
pyats/manifest/runtime.cpython-310-x86_64-linux-gnu.so
pyats/manifest/schema.cpython-310-x86_64-linux-gnu.so
pyats-25.9.dist-info/METADATA
pyats-25.9.dist-info/WHEEL
pyats-25.9.dist-info/entry_points.txt
pyats-25.9.dist-info/top_level.txt
pyats-25.9.dist-info/RECORD
