Metadata-Version: 2.1
Name: pyats
Version: 25.9
Summary: pyATS - Python Automation Test System
Home-page: https://developer.cisco.com/pyats/
Author: Cisco Systems Inc.
Author-email: pyats-support-ext@cisco.com
License: Apache 2.0
Keywords: pyats test automation
Classifier: Development Status :: 6 - Mature
Classifier: Development Status :: 5 - Production/Stable
Classifier: Environment :: Console
Classifier: Intended Audience :: Developers
Classifier: Intended Audience :: Telecommunications Industry
Classifier: Intended Audience :: Information Technology
Classifier: Intended Audience :: System Administrators
Classifier: License :: OSI Approved :: Apache Software License
Classifier: Operating System :: MacOS
Classifier: Operating System :: POSIX :: Linux
Classifier: Programming Language :: Python :: 3.13
Classifier: Programming Language :: Python :: 3.12
Classifier: Programming Language :: Python :: 3.11
Classifier: Programming Language :: Python :: 3.10
Classifier: Programming Language :: Python :: 3.9
Classifier: Programming Language :: Python :: 3 :: Only
Classifier: Programming Language :: Python :: Implementation :: CPython
Classifier: Topic :: Software Development :: Testing
Classifier: Topic :: Software Development :: Build Tools
Classifier: Topic :: Software Development :: Libraries
Classifier: Topic :: Software Development :: Libraries :: Python Modules
Requires-Python: >=3.8
Requires-Dist: packaging>=20.0
Requires-Dist: pyats.aereport<25.10.0,>=25.9.0
Requires-Dist: pyats.aetest<25.10.0,>=25.9.0
Requires-Dist: pyats.async<25.10.0,>=25.9.0
Requires-Dist: pyats.log<25.10.0,>=25.9.0
Requires-Dist: pyats.kleenex<25.10.0,>=25.9.0
Requires-Dist: pyats.connections<25.10.0,>=25.9.0
Requires-Dist: pyats.datastructures<25.10.0,>=25.9.0
Requires-Dist: pyats.easypy<25.10.0,>=25.9.0
Requires-Dist: pyats.results<25.10.0,>=25.9.0
Requires-Dist: pyats.reporter<25.10.0,>=25.9.0
Requires-Dist: pyats.tcl<25.10.0,>=25.9.0
Requires-Dist: pyats.topology<25.10.0,>=25.9.0
Requires-Dist: pyats.utils<25.10.0,>=25.9.0
Provides-Extra: full
Requires-Dist: cookiecutter; extra == "full"
Requires-Dist: genie<25.10.0,>=25.9.0; extra == "full"
Requires-Dist: pyats.robot<25.10.0,>=25.9.0; extra == "full"
Requires-Dist: genie.libs.robot<25.10.0,>=25.9.0; extra == "full"
Requires-Dist: genie.telemetry<25.10.0,>=25.9.0; extra == "full"
Requires-Dist: genie.trafficgen<25.10.0,>=25.9.0; extra == "full"
Requires-Dist: pyats.contrib<25.10.0,>=25.9.0; extra == "full"
Provides-Extra: library
Requires-Dist: genie<25.10.0,>=25.9.0; extra == "library"
Provides-Extra: robot
Requires-Dist: pyats.robot<25.10.0,>=25.9.0; extra == "robot"
Requires-Dist: genie.libs.robot<25.10.0,>=25.9.0; extra == "robot"
Provides-Extra: template
Requires-Dist: cookiecutter; extra == "template"
